AutoPoly/__init__.py
AutoPoly/conf.py
AutoPoly/logger.py
AutoPoly/polymer.py
AutoPoly/polymerization.py
AutoPoly/system.py
AutoPoly/extern/__init__.py
AutoPoly/extern/rdlt.py
AutoPoly-0.0.1.dist-info/METADATA
AutoPoly-0.0.1.dist-info/WHEEL
AutoPoly-0.0.1.dist-info/top_level.txt
AutoPoly-0.0.1.dist-info/RECORD
