Metadata-Version: 2.1
Name: AutoPoly
Version: 0.0.1
Summary: AutoPoly
Home-page: UNKNOWN
Author: Zhenghao Wu
Author-email: zhenghao.wu95@gmail.com
License: UNKNOWN
Keywords: python,molecular dynamics
Platform: UNKNOWN
Requires-Dist: numpy (>=1.8.0)
Requires-Dist: rdkit (>=2022.09.1)
Requires-Dist: pathlib (>=1.0.1)
